nanoporeAlignment/__init__.py
nanoporeAlignment/nanoAlign.py
primer_design/__init__.py
primer_design/primerdesign.py
nanoSeq-0.1.dist-info/LICENSE.txt
nanoSeq-0.1.dist-info/METADATA
nanoSeq-0.1.dist-info/WHEEL
nanoSeq-0.1.dist-info/entry_points.txt
nanoSeq-0.1.dist-info/top_level.txt
nanoSeq-0.1.dist-info/RECORD
